yefpy/__init__.py
yefpy/cfg.py
yefpy/gen_start_sh.py
yefpy/generate.py
yefpy/gotypes.py
yefpy/mod_data.py
yefpy/yef.py
yefpy_uwine-0.1.0.dist-info/METADATA
yefpy_uwine-0.1.0.dist-info/WHEEL
yefpy_uwine-0.1.0.dist-info/top_level.txt
yefpy_uwine-0.1.0.dist-info/RECORD
