Metadata-Version: 2.1
Name: yefpy-uwine
Version: 0.1.0
Summary: yefpy project.
Classifier: Programming Language :: Python :: 3
Requires-Python: >=3.7
Requires-Dist: ruamel.yaml
